roar_cli-0.2.1.data/purelib/roar/__init__.py
roar_cli-0.2.1.data/purelib/roar/__main__.py
roar_cli-0.2.1.data/purelib/roar/config.py
roar_cli-0.2.1.data/purelib/roar/glaas_client.py
roar_cli-0.2.1.data/purelib/roar/analyzers/__init__.py
roar_cli-0.2.1.data/purelib/roar/analyzers/base.py
roar_cli-0.2.1.data/purelib/roar/analyzers/experiment_trackers.py
roar_cli-0.2.1.data/purelib/roar/bin/roar-tracer
roar_cli-0.2.1.data/purelib/roar/cli/__init__.py
roar_cli-0.2.1.data/purelib/roar/cli/context.py
roar_cli-0.2.1.data/purelib/roar/cli/decorators.py
roar_cli-0.2.1.data/purelib/roar/cli/commands/__init__.py
roar_cli-0.2.1.data/purelib/roar/cli/commands/_execution.py
roar_cli-0.2.1.data/purelib/roar/cli/commands/auth.py
roar_cli-0.2.1.data/purelib/roar/cli/commands/build.py
roar_cli-0.2.1.data/purelib/roar/cli/commands/config.py
roar_cli-0.2.1.data/purelib/roar/cli/commands/dag.py
roar_cli-0.2.1.data/purelib/roar/cli/commands/env.py
roar_cli-0.2.1.data/purelib/roar/cli/commands/init.py
roar_cli-0.2.1.data/purelib/roar/cli/commands/lineage.py
roar_cli-0.2.1.data/purelib/roar/cli/commands/log.py
roar_cli-0.2.1.data/purelib/roar/cli/commands/pop.py
roar_cli-0.2.1.data/purelib/roar/cli/commands/register.py
roar_cli-0.2.1.data/purelib/roar/cli/commands/reproduce.py
roar_cli-0.2.1.data/purelib/roar/cli/commands/reset.py
roar_cli-0.2.1.data/purelib/roar/cli/commands/run.py
roar_cli-0.2.1.data/purelib/roar/cli/commands/show.py
roar_cli-0.2.1.data/purelib/roar/cli/commands/status.py
roar_cli-0.2.1.data/purelib/roar/core/__init__.py
roar_cli-0.2.1.data/purelib/roar/core/bootstrap.py
roar_cli-0.2.1.data/purelib/roar/core/container.py
roar_cli-0.2.1.data/purelib/roar/core/di.py
roar_cli-0.2.1.data/purelib/roar/core/exceptions.py
roar_cli-0.2.1.data/purelib/roar/core/registry.py
roar_cli-0.2.1.data/purelib/roar/core/settings.py
roar_cli-0.2.1.data/purelib/roar/core/validation.py
roar_cli-0.2.1.data/purelib/roar/core/dto/__init__.py
roar_cli-0.2.1.dist-info/licenses/LICENSE
roar_cli-0.2.1.dist-info/METADATA
roar_cli-0.2.1.dist-info/WHEEL
roar_cli-0.2.1.dist-info/entry_points.txt
roar_cli-0.2.1.dist-info/top_level.txt
roar_cli-0.2.1.dist-info/RECORD
