Metadata-Version: 2.4
Name: roar-cli
Version: 0.2.1
Summary: Reproducibility and provenance tracker for ML training pipelines
Author-email: TReqs Team <info@treqs.ai>
License-Expression: Apache-2.0
Project-URL: Homepage, https://github.com/treqs/roar
Project-URL: Repository, https://github.com/treqs/roar
Project-URL: Documentation, https://github.com/treqs/roar#readme
Project-URL: Issues, https://github.com/treqs/roar/issues
Keywords: machine-learning,reproducibility,lineage,provenance,mlops,data-versioning,artifact-tracking
Classifier: Development Status :: 3 - Alpha
Classifier: Intended Audience :: Developers
Classifier: Intended Audience :: Science/Research
Classifier: Operating System :: OS Independent
Classifier: Programming Language :: Python :: 3
Classifier: Programming Language :: Python :: 3.10
Classifier: Programming Language :: Python :: 3.11
Classifier: Programming Language :: Python :: 3.12
Classifier: Programming Language :: Python :: 3.13
Classifier: Topic :: Scientific/Engineering :: Artificial Intelligence
Classifier: Topic :: Software Development :: Version Control
Classifier: Typing :: Typed
Requires-Python: >=3.10
License-File: LICENSE
Requires-Dist: blake3>=0.3.0
Requires-Dist: click>=8.1.0
Requires-Dist: dependency-injector>=4.40.0
Requires-Dist: sqlalchemy>=2.0.0
Requires-Dist: pysqlite3-binary>=0.5.0
Requires-Dist: pydantic>=2.0.0
Requires-Dist: pydantic-settings>=2.0.0
Requires-Dist: tomli>=2.0.0; python_version < "3.11"
Provides-Extra: dev
Requires-Dist: pytest>=7.0.0; extra == "dev"
Requires-Dist: pytest-timeout>=2.0.0; extra == "dev"
Requires-Dist: pytest-mock>=3.10.0; extra == "dev"
Requires-Dist: pytest-cov>=4.0.0; extra == "dev"
Requires-Dist: pytest-xdist>=3.5.0; extra == "dev"
Requires-Dist: ruff>=0.8.0; extra == "dev"
Requires-Dist: mypy>=1.13.0; extra == "dev"
Dynamic: license-file
